crybaby/__init__.py
crybaby/exceptions.py
crybaby-0.0.8.dist-info/METADATA
crybaby-0.0.8.dist-info/WHEEL
crybaby-0.0.8.dist-info/licenses/LICENSE
crybaby-0.0.8.dist-info/RECORD
