Metadata-Version: 2.1
Name: crybaby
Version: 0.0.8
Summary: Python exception handler that sends error messages to Slack.
Project-URL: homepage, https://github.com/jujumilk3/crybaby
Project-URL: bug-tracker, https://github.com/jujumilk3/crybaby/issues
Author-email: gyudoza <jujumilk3@gmail.com>
License-Expression: MIT
License-File: LICENSE
Classifier: License :: OSI Approved :: MIT License
Classifier: Programming Language :: Python
Classifier: Programming Language :: Python :: 3
Classifier: Programming Language :: Python :: 3 :: Only
Classifier: Programming Language :: Python :: 3.6
Classifier: Programming Language :: Python :: 3.7
Classifier: Programming Language :: Python :: 3.8
Classifier: Programming Language :: Python :: 3.9
Classifier: Programming Language :: Python :: 3.10
Classifier: Programming Language :: Python :: 3.11
Classifier: Topic :: Software Development :: Libraries :: Python Modules
Classifier: Typing :: Typed
Requires-Python: >=3.6.0
Requires-Dist: requests
Provides-Extra: dev
Requires-Dist: pytest; extra == 'dev'
Requires-Dist: twine; extra == 'dev'
Provides-Extra: test
Requires-Dist: black; extra == 'test'
Requires-Dist: isort; extra == 'test'
Requires-Dist: pytest; extra == 'test'
Requires-Dist: requests-mock; extra == 'test'
